{"cameraMode":{"drawMode":0,"name":"Shaded","section":"Shading Mode"},"sceneLighting":false,"audioPlay":false,"sceneViewState":{"m_AlwaysRefresh":false,"showFog":true,"showSkybox":false,"showFlares":true,"showImageEffects":true,"showParticleSystems":true,"showVisualEffectGraphs":true,"m_FxEnabled":true},"in2DMode":false,"pivot":{"x":1.5643497705459595,"y":-0.8352130651473999,"z":-0.9825171232223511},"rotation":{"x":0.2964484989643097,"y":0.3052383363246918,"z":-0.10064204782247544,"w":0.8993797302246094},"size":4.003360748291016,"orthographic":false}